pactverify/__init__.py
pactverify/core.py
pactverify/matchers.py
pactverify/utils.py
pactverify-2.0.1.dist-info/LICENSE
pactverify-2.0.1.dist-info/METADATA
pactverify-2.0.1.dist-info/WHEEL
pactverify-2.0.1.dist-info/top_level.txt
pactverify-2.0.1.dist-info/RECORD
