Metadata-Version: 2.1
Name: pactverify
Version: 2.0.1
Summary: 接口断言契约校验
Home-page: https://github.com/xglh/PactVerify_demo
Author: liuhui
Author-email: 1318633361@qq.com
License: UNKNOWN
Platform: UNKNOWN
Classifier: Programming Language :: Python :: 3
Classifier: License :: OSI Approved :: MIT License
Classifier: Operating System :: OS Independent
